ssquant/SQDATA.py
ssquant/__init__.py
ssquant-1.0.2.dist-info/LICENSE
ssquant-1.0.2.dist-info/METADATA
ssquant-1.0.2.dist-info/WHEEL
ssquant-1.0.2.dist-info/top_level.txt
ssquant-1.0.2.dist-info/RECORD
