Metadata-Version: 2.1
Name: ssquant
Version: 1.0.2
Summary: woyebuzhidao
Home-page: https://github.com/a7088044/ssquant
Author: 17703460872
Author-email: 339093103@qq.com
License: MIT
Classifier: License :: OSI Approved :: MIT License
Classifier: Programming Language :: Python
Classifier: Programming Language :: Python :: 3
Classifier: Programming Language :: Python :: 3.6
Classifier: Programming Language :: Python :: Implementation :: CPython
Classifier: Programming Language :: Python :: Implementation :: PyPy
Requires-Python: >=3.6.0
License-File: LICENSE
Requires-Dist: requests
Requires-Dist: pandas
